simonsays_drgreengiant/__init__.py
simonsays_drgreengiant/__main__.py
simonsays_drgreengiant/actions.py
simonsays_drgreengiant/config.py
simonsays_drgreengiant/environment.py
simonsays_drgreengiant/errorcodes.py
simonsays_drgreengiant/gameactions.py
simonsays_drgreengiant/gui.py
simonsays_drgreengiant/hidactions.py
simonsays_drgreengiant/simonsays.py
simonsays_drgreengiant/twitchactions.py
simonsays_drgreengiant/phasmoactions/crouch.py
simonsays_drgreengiant/phasmoactions/defaults.py
simonsays_drgreengiant/phasmoactions/drop.py
simonsays_drgreengiant/phasmoactions/journal.py
simonsays_drgreengiant/phasmoactions/look.py
simonsays_drgreengiant/phasmoactions/peek.py
simonsays_drgreengiant/phasmoactions/phasmoactions.py
simonsays_drgreengiant/phasmoactions/pickup.py
simonsays_drgreengiant/phasmoactions/place.py
simonsays_drgreengiant/phasmoactions/radio.py
simonsays_drgreengiant/phasmoactions/sprint.py
simonsays_drgreengiant/phasmoactions/switch.py
simonsays_drgreengiant/phasmoactions/talk.py
simonsays_drgreengiant/phasmoactions/torch.py
simonsays_drgreengiant/phasmoactions/use.py
simonsays_drgreengiant/phasmoactions/walk.py
simonsays_drgreengiant/phasmoactions/combos/box.py
simonsays_drgreengiant/phasmoactions/combos/cycle.py
simonsays_drgreengiant/phasmoactions/combos/cycleuse.py
simonsays_drgreengiant/phasmoactions/combos/disco.py
simonsays_drgreengiant/phasmoactions/combos/dropall.py
simonsays_drgreengiant/phasmoactions/combos/feet.py
simonsays_drgreengiant/phasmoactions/combos/freeze.py
simonsays_drgreengiant/phasmoactions/combos/headbang.py
simonsays_drgreengiant/phasmoactions/combos/headshake.py
simonsays_drgreengiant/phasmoactions/combos/hurricane.py
simonsays_drgreengiant/phasmoactions/combos/spin.py
simonsays_drgreengiant/phasmoactions/combos/teabag.py
simonsays_drgreengiant/phasmoactions/combos/tornado.py
simonsays_drgreengiant/phasmoactions/combos/yoga.py
simonsays_drgreengiant-2.1.0.dist-info/LICENSE
simonsays_drgreengiant-2.1.0.dist-info/METADATA
simonsays_drgreengiant-2.1.0.dist-info/WHEEL
simonsays_drgreengiant-2.1.0.dist-info/top_level.txt
simonsays_drgreengiant-2.1.0.dist-info/RECORD
