Metadata-Version: 2.1
Name: simonsays_drgreengiant
Version: 2.1.0
Summary: A Twitch Plays style programme to allow users in Twitch chats to control the broadcasters mouse and keyboard
Author-email: Simon Howroyd <howroydlsu@gmail.com>
Project-URL: Homepage, https://github.com/howroyd/simonsays
Project-URL: Repository, https://github.com/howroyd/simonsays
Project-URL: Bug Tracker, https://github.com/howroyd/simonsays/issues
Keywords: twitch,chat,twitchplays,troll
Classifier: Development Status :: 5 - Production/Stable
Classifier: Framework :: Pytest
Classifier: License :: OSI Approved :: GNU General Public License v2 (GPLv2)
Classifier: Natural Language :: English
Classifier: Operating System :: OS Independent
Classifier: Programming Language :: Python :: 3.11
Classifier: Topic :: Communications :: Chat :: Internet Relay Chat
Classifier: Topic :: Games/Entertainment
Requires-Python: >=3.11.4
License-File: LICENSE
Requires-Dist: Pillow
Requires-Dist: pynput
Requires-Dist: requests
Requires-Dist: semantic-version
Requires-Dist: tomlkit
Requires-Dist: twitchirc-drgreengiant
Provides-Extra: dev
Requires-Dist: ruff ; extra == 'dev'
